{
	"animations": [
		{
			"offsets": [
				0,
				-20
			],
			"loop": true,
			"fps": 18,
			"anim": "idle",
			"indices": [],
			"name": "i"
		},
		{
			"offsets": [
				69,
				-24
			],
			"loop": false,
			"fps": 20,
			"anim": "singLEFT",
			"indices": [],
			"name": "l"
		},
		{
			"offsets": [
				23,
				-77
			],
			"loop": false,
			"fps": 20,
			"anim": "singDOWN",
			"indices": [],
			"name": "d0"
		},
		{
			"offsets": [
				83,
				52
			],
			"loop": false,
			"fps": 20,
			"anim": "singUP",
			"indices": [],
			"name": "u"
		},
		{
			"offsets": [
				2,
				-23
			],
			"loop": false,
			"fps": 20,
			"anim": "singRIGHT",
			"indices": [],
			"name": "r"
		}
	],
	"vocals_file": "",
	"no_antialiasing": true,
	"image": "characters/black2",
	"position": [
		100,
		340
	],
	"healthicon": "face",
	"flip_x": false,
	"healthbar_colors": [
		161,
		161,
		161
	],
	"camera_position": [
		-190,
		0
	],
	"sing_duration": 6.1,
	"scale": 1,
	"_editor_isPlayer": false
}